{
    "Teapot": {
        "01eef9b0f1829ee0": {
            "hash": "01eef9b0f1829ee0",
            "directory": "External0",
            "voiceContent": "嗯…口感是很重要的一部分",
            "sourceName": "vo_kaeya_mimitomo_friendship2_04.wem"
        },
        "03778cb62006fd75": {
            "hash": "03778cb62006fd75",
            "directory": "External0",
            "voiceContent": "#唷，{NICKNAME}",
            "sourceName": "vo_kaeya_mimitomo_hello_01.wem"
        },
        "103caecf2c0eed2d": {
            "hash": "103caecf2c0eed2d",
            "directory": "External2",
            "voiceContent": "到时候也这样陪我聊两句吧，朋友",
            "sourceName": "vo_mimiTomo_md_kaeya_park_03.wem"
        },
        "136b0777f8b5d3b3": {
            "hash": "136b0777f8b5d3b3",
            "directory": "External2",
            "voiceContent": "唔…要是手边有杯酒就更好了啊",
            "sourceName": "vo_kaeya_mimitomo_friendship2_03.wem"
        },
        "14b12ff257d5d898": {
            "hash": "14b12ff257d5d898",
            "directory": "External2",
            "voiceContent": "看来我要早点开工了啊",
            "sourceName": "vo_kaeya_mimitomo_friendship3_07.wem"
        },
        "262a5be14829b0b6": {
            "hash": "262a5be14829b0b6",
            "directory": "External4",
            "voiceContent": "将居家旅行的实用知识收纳其中，我所总结出的三教九流交流技巧也可以尽数分享给你",
            "sourceName": "vo_kaeya_mimitomo_friendship3_05.wem"
        },
        "2f4962a109514fe2": {
            "hash": "2f4962a109514fe2",
            "directory": "External5",
            "voiceContent": "哎——瞧你这说的。我哪有那么多痛苦的事情",
            "sourceName": "vo_kaeya_mimitomo_friendship2_06b_1.wem"
        },
        "3870123d46806787": {
            "hash": "3870123d46806787",
            "directory": "External7",
            "voiceContent": "已经那么快就到晚上了吗。真有点舍不得",
            "sourceName": "vo_kaeya_mimitomo_night_01.wem"
        },
        "3ac45b3011b9997c": {
            "hash": "3ac45b3011b9997c",
            "directory": "External7",
            "voiceContent": "听候你的差遣",
            "sourceName": "vo_kaeya_mimitomo_friendship3_03b_1.wem"
        },
        "49459726314b0c0d": {
            "hash": "49459726314b0c0d",
            "directory": "External9",
            "voiceContent": "#嗯，早啊，{NICKNAME}",
            "sourceName": "vo_kaeya_mimitomo_morning_01.wem"
        },
        "4b738344ccc3b905": {
            "hash": "4b738344ccc3b905",
            "directory": "External9",
            "voiceContent": "所以…我只是比较贪心吧。想要让这些快乐的事情叠加在一起",
            "sourceName": "vo_kaeya_mimitomo_friendship2_09.wem"
        },
        "4d003da021702cac": {
            "hash": "4d003da021702cac",
            "directory": "External9",
            "voiceContent": "但酒的作用是衬托你",
            "sourceName": "vo_kaeya_mimitomo_friendship2_13.wem"
        },
        "4dce0e4c9c3cfd98": {
            "hash": "4dce0e4c9c3cfd98",
            "directory": "External9",
            "voiceContent": "我说的可都是我的真心话",
            "sourceName": "vo_kaeya_mimitomo_friendship3_03a_2.wem"
        },
        "4f002c983ac23520": {
            "hash": "4f002c983ac23520",
            "directory": "External9",
            "voiceContent": "这里比我当初想象得更漂亮",
            "sourceName": "vo_kaeya_mimitomo_friendship1_05.wem"
        },
        "5d163a5f3f1241f3": {
            "hash": "5d163a5f3f1241f3",
            "directory": "External11",
            "voiceContent": "唔，只说「习惯」的话怎么想都会觉得程度不够吧",
            "sourceName": "vo_kaeya_mimitomo_friendship1_02.wem"
        },
        "60e5349cce7d85b0": {
            "hash": "60e5349cce7d85b0",
            "directory": "External12",
            "voiceContent": "…呵呵，想起了从前在酒庄的日子",
            "sourceName": "vo_mimiTomo_md_kaeya_vineyard_02.wem"
        },
        "61df398f14a6dc7a": {
            "hash": "61df398f14a6dc7a",
            "directory": "External12",
            "voiceContent": "我想想",
            "sourceName": "vo_kaeya_mimitomo_friendship2_11.wem"
        },
        "63d042bff58c44b3": {
            "hash": "63d042bff58c44b3",
            "directory": "External12",
            "voiceContent": "呆在这里感觉好像身在蒙德，唯一不同的就是不会有团里的差事烦心",
            "sourceName": "vo_mimiTomo_md_kaeya_park_01.wem"
        },
        "6bb184dbb2bf7e7c": {
            "hash": "6bb184dbb2bf7e7c",
            "directory": "External13",
            "voiceContent": "嗯，没错",
            "sourceName": "vo_kaeya_mimitomo_friendship1_04a.wem"
        },
        "74b8a2ee1dad7ce6": {
            "hash": "74b8a2ee1dad7ce6",
            "directory": "External14",
            "voiceContent": "你果然有过人的天赋啊",
            "sourceName": "vo_kaeya_mimitomo_friendship2_06a_2.wem"
        },
        "752ecbc064433502": {
            "hash": "752ecbc064433502",
            "directory": "External14",
            "voiceContent": "我嘛，只要有你在身边就满足了",
            "sourceName": "vo_kaeya_mimitomo_friendship3_01.wem"
        },
        "7cf42eacb5d40012": {
            "hash": "7cf42eacb5d40012",
            "directory": "External15",
            "voiceContent": "没想到又见到你了",
            "sourceName": "vo_kaeya_mimitomo_hello_02.wem"
        },
        "7f3c3dd7cc3c321f": {
            "hash": "7f3c3dd7cc3c321f",
            "directory": "External15",
            "voiceContent": "哦，对了。要不要为你编写一本指南呢",
            "sourceName": "vo_kaeya_mimitomo_friendship3_04.wem"
        },
        "89bb80a93813e605": {
            "hash": "89bb80a93813e605",
            "directory": "External17",
            "voiceContent": "对于现在的生活，我可是很知足的",
            "sourceName": "vo_kaeya_mimitomo_friendship2_06b_2.wem"
        },
        "8e7dd580396060aa": {
            "hash": "8e7dd580396060aa",
            "directory": "External17",
            "voiceContent": "说吧，我很乐意奉陪",
            "sourceName": "vo_kaeya_mimitomo_friendship2_02.wem"
        },
        "8f30a455fbd3c520": {
            "hash": "8f30a455fbd3c520",
            "directory": "External17",
            "voiceContent": "嗯…休息好才会有精神。好啦，晚安",
            "sourceName": "vo_kaeya_mimitomo_night_02.wem"
        },
        "966e89ea1475f619": {
            "hash": "966e89ea1475f619",
            "directory": "External18",
            "voiceContent": "哈哈…谢谢",
            "sourceName": "vo_kaeya_mimitomo_friendship3_06.wem"
        },
        "9e038c7756d9ebdc": {
            "hash": "9e038c7756d9ebdc",
            "directory": "External19",
            "voiceContent": "哦，习惯得很",
            "sourceName": "vo_kaeya_mimitomo_friendship1_01.wem"
        },
        "9f2d7889015be9fe": {
            "hash": "9f2d7889015be9fe",
            "directory": "External19",
            "voiceContent": "真是难得啊",
            "sourceName": "vo_kaeya_mimitomo_friendship1_07.wem"
        },
        "a15894d80a72789c": {
            "hash": "a15894d80a72789c",
            "directory": "External20",
            "voiceContent": "带上陈年的美酒，在这里品尝的话，那就太惬意了",
            "sourceName": "vo_mimiTomo_md_kaeya_park_02.wem"
        },
        "ab2e67983c2f4147": {
            "hash": "ab2e67983c2f4147",
            "directory": "External21",
            "voiceContent": "话说回来，跟你聊天是一件很让人陶醉的事情",
            "sourceName": "vo_kaeya_mimitomo_friendship2_07.wem"
        },
        "ae4baa1aa8aa5a02": {
            "hash": "ae4baa1aa8aa5a02",
            "directory": "External21",
            "voiceContent": "这说明你信任我，也说明我有这种为你解决问题的能力",
            "sourceName": "vo_kaeya_mimitomo_friendship3_03a_4.wem"
        },
        "afbe53a9e9946861": {
            "hash": "afbe53a9e9946861",
            "directory": "External21",
            "voiceContent": "不过，也有一部分原因是喜欢喝酒的感觉",
            "sourceName": "vo_kaeya_mimitomo_friendship2_05.wem"
        },
        "b7546b8595a77a43": {
            "hash": "b7546b8595a77a43",
            "directory": "External22",
            "voiceContent": "哈哈…有意思有意思。是我没有思考过的角度",
            "sourceName": "vo_kaeya_mimitomo_friendship2_10.wem"
        },
        "b8591c3210a3571f": {
            "hash": "b8591c3210a3571f",
            "directory": "External23",
            "voiceContent": "哈，哪里哪里",
            "sourceName": "vo_kaeya_mimitomo_friendship3_03a_1.wem"
        },
        "bbe45797430ca17d": {
            "hash": "bbe45797430ca17d",
            "directory": "External23",
            "voiceContent": "嗯…可能会吧",
            "sourceName": "vo_kaeya_mimitomo_friendship2_12.wem"
        },
        "bfd773872f387c2d": {
            "hash": "bfd773872f387c2d",
            "directory": "External23",
            "voiceContent": "哦？那你可是找对人了",
            "sourceName": "vo_kaeya_mimitomo_friendship2_01.wem"
        },
        "c32f791cc7754e0a": {
            "hash": "c32f791cc7754e0a",
            "directory": "External24",
            "voiceContent": "如果想找个倾诉的对象，别忘了还有我",
            "sourceName": "vo_kaeya_mimitomo_morning_02.wem"
        },
        "cf8b684458dd1b19": {
            "hash": "cf8b684458dd1b19",
            "directory": "External25",
            "voiceContent": "如果我的点子对你起到了什么帮助，那感到自豪的可是我本人",
            "sourceName": "vo_kaeya_mimitomo_friendship3_03a_3.wem"
        },
        "cf9fe9c893041925": {
            "hash": "cf9fe9c893041925",
            "directory": "External25",
            "voiceContent": "#倒是有什么能为你效劳的吗？{NICKNAME}",
            "sourceName": "vo_kaeya_mimitomo_friendship3_02.wem"
        },
        "d605b2c126f6cb13": {
            "hash": "d605b2c126f6cb13",
            "directory": "External26",
            "voiceContent": "哎——当然是惊喜的那种啦",
            "sourceName": "vo_kaeya_mimitomo_friendship1_04b.wem"
        },
        "db8f0867829ff7ea": {
            "hash": "db8f0867829ff7ea",
            "directory": "External27",
            "voiceContent": "最初的确是「大吃一惊」",
            "sourceName": "vo_kaeya_mimitomo_friendship1_03.wem"
        },
        "e178a282e09ba517": {
            "hash": "e178a282e09ba517",
            "directory": "External28",
            "voiceContent": "答应我，葡萄熟了，可别用来榨汁，酿成美酒才算物尽其用",
            "sourceName": "vo_mimiTomo_md_kaeya_vineyard_01.wem"
        },
        "e4fcd0f6e9f9c249": {
            "hash": "e4fcd0f6e9f9c249",
            "directory": "External28",
            "voiceContent": "哦？明明没有实践却能单纯通过话语理解",
            "sourceName": "vo_kaeya_mimitomo_friendship2_06a_1.wem"
        },
        "e6088e948e00cc31": {
            "hash": "e6088e948e00cc31",
            "directory": "External28",
            "voiceContent": "不如我来和你分享分享，酿酒的秘诀吧",
            "sourceName": "vo_mimiTomo_md_kaeya_vineyard_03.wem"
        },
        "f22b494e488312b4": {
            "hash": "f22b494e488312b4",
            "directory": "External30",
            "voiceContent": "喝酒对我来说也一样",
            "sourceName": "vo_kaeya_mimitomo_friendship2_08.wem"
        },
        "f83f9a7f856ed787": {
            "hash": "f83f9a7f856ed787",
            "directory": "External31",
            "voiceContent": "但是，待的时间长了，吃惊的感觉没留下多少。倒是因为这种自在，产生了点归属感",
            "sourceName": "vo_kaeya_mimitomo_friendship1_06.wem"
        }
    },
    "Quests": {
        "18ca7d868b06d9bc": {
            "hash": "18ca7d868b06d9bc",
            "directory": "External3",
            "voiceContent": "（非如此不可…哈哈，非如此不可！",
            "sourceName": "vo_KYCOP001_1909806_kaeya_01.wem"
        },
        "205e833f1e6e7198": {
            "hash": "205e833f1e6e7198",
            "directory": "External4",
            "voiceContent": "…常年做善后工作积累下来的经验",
            "sourceName": "vo_MDAQ030_5_kaeya_03.wem"
        },
        "30ae831c64419254": {
            "hash": "30ae831c64419254",
            "directory": "External6",
            "voiceContent": "没错，相当敏锐的观察",
            "sourceName": "vo_MDAQ030_5_kaeya_07.wem"
        },
        "31d7af2e0ec249b6": {
            "hash": "31d7af2e0ec249b6",
            "directory": "External6",
            "voiceContent": "如果我猜的没错，庙宇的尽头就在那里",
            "sourceName": "vo_MDAQ030_5_kaeya_01.wem"
        },
        "3e6f2168cbed1667": {
            "hash": "3e6f2168cbed1667",
            "directory": "External7",
            "voiceContent": "不如让琴为你授衔，成为骑士吧",
            "sourceName": "vo_MDAQ030_5_kaeya_08.wem"
        },
        "5bddb3ac68c02fe4": {
            "hash": "5bddb3ac68c02fe4",
            "directory": "External11",
            "voiceContent": "要说我来这里的原因，大概是琴在为外贸安全问题发愁的时候，我正好闯进了团长办公室吧",
            "sourceName": "vo_KYCOP001_1907303_kaeya_01.wem"
        },
        "6cbd3269eefb5d1b": {
            "hash": "6cbd3269eefb5d1b",
            "directory": "External13",
            "voiceContent": "（看戏…算是不错的娱乐吧，可惜故事我都已经知道了。",
            "sourceName": "vo_KYCOP001_1909803_kaeya_01.wem"
        },
        "7c6d0bfce6f78b67": {
            "hash": "7c6d0bfce6f78b67",
            "directory": "External15",
            "voiceContent": "（在事情变得更无聊之前，早点脱身为好。",
            "sourceName": "vo_KYCOP001_1909807_kaeya_01.wem"
        },
        "9b8c527b76c1135d": {
            "hash": "9b8c527b76c1135d",
            "directory": "External19",
            "voiceContent": "巴顿，结账",
            "sourceName": "vo_KYCOP001_1909403_kaeya_18.wem"
        },
        "a21bdd36db0e8f19": {
            "hash": "a21bdd36db0e8f19",
            "directory": "External20",
            "voiceContent": "经验",
            "sourceName": "vo_MDAQ030_5_kaeya_02.wem"
        },
        "c4eb211771172b5c": {
            "hash": "c4eb211771172b5c",
            "directory": "External24",
            "voiceContent": "很有可能，赶紧动手吧",
            "sourceName": "vo_MDAQ031_6_kaeya_01.wem"
        },
        "d9420192782a325b": {
            "hash": "d9420192782a325b",
            "directory": "External27",
            "voiceContent": "没办法，只能怪我太有责任心，这次出远门的活又落到我头上来了",
            "sourceName": "vo_KYCOP001_1907303_kaeya_02.wem"
        },
        "da241103af1bfacb": {
            "hash": "da241103af1bfacb",
            "directory": "External27",
            "voiceContent": "前面没有路了。靠风场上去吧",
            "sourceName": "vo_MDAQ030_5_kaeya_04.wem"
        },
        "ebf2e483dcae31a4": {
            "hash": "ebf2e483dcae31a4",
            "directory": "External29",
            "voiceContent": "#（不过有{NICKNAME}作陪应该不会无聊。离风暴的中心越近就越让人心跳加速，呵呵。",
            "sourceName": "vo_KYCOP001_1909803_kaeya_02.wem"
        },
        "ed43efbde0756595": {
            "hash": "ed43efbde0756595",
            "directory": "External29",
            "voiceContent": "（好无聊啊，就没点有趣的事吗？",
            "sourceName": "vo_KYCOP001_1907302_kaeya_07.wem"
        }
    },
    "Gameplay": {
        "03c11b9dc5bf4e61": {
            "hash": "03c11b9dc5bf4e61",
            "directory": "External0",
            "voiceContent": "SF",
            "sourceName": "vo_kaeya_battle_attackmid_03.wem"
        },
        "06187fd637e8a03c": {
            "hash": "06187fd637e8a03c",
            "directory": "External0",
            "voiceContent": "哎呀，你还有两下子",
            "sourceName": "vo_card_kaeya_inGame_easy_02.wem"
        },
        "0892a2c041a2f6c0": {
            "hash": "0892a2c041a2f6c0",
            "directory": "External1",
            "voiceContent": "SF",
            "sourceName": "vo_kaeya_explore_fly_start_05.wem"
        },
        "0eff1392b13673fa": {
            "hash": "0eff1392b13673fa",
            "directory": "External1",
            "voiceContent": "SF",
            "sourceName": "vo_kaeya_battle_hit_l_04.wem"
        },
        "119d27b320305722": {
            "hash": "119d27b320305722",
            "directory": "External2",
            "voiceContent": "放心，我只是吃得慢了一点，我会好好吃完的",
            "sourceName": "vo_kaeya_spice_dislike_01.wem"
        },
        "125a11cece990ed9": {
            "hash": "125a11cece990ed9",
            "directory": "External2",
            "voiceContent": "SF",
            "sourceName": "vo_kaeya_explore_climb_03.wem"
        },
        "128239d9ae21b757": {
            "hash": "128239d9ae21b757",
            "directory": "External2",
            "voiceContent": "还没尽…兴",
            "sourceName": "vo_kaeya_life_die_01.wem"
        },
        "13ac25eb58a3b571": {
            "hash": "13ac25eb58a3b571",
            "directory": "External2",
            "voiceContent": "太难看了",
            "sourceName": "vo_kaeya_life_die_03.wem"
        },
        "1437329713b9f145": {
            "hash": "1437329713b9f145",
            "directory": "External2",
            "voiceContent": "SF",
            "sourceName": "vo_kaeya_battle_attacklight_01.wem"
        },
        "156f563a765d1b81": {
            "hash": "156f563a765d1b81",
            "directory": "External2",
            "voiceContent": "挺有趣的",
            "sourceName": "vo_kaeya_chest_open_02.wem"
        },
        "17da68b9db4bc222": {
            "hash": "17da68b9db4bc222",
            "directory": "External2",
            "voiceContent": "我的眼睛？我的眼睛没事。想把身体的某些部分遮起来是很平常的事儿吧？衣服和裤子也是一个道理",
            "sourceName": "vo_kaeya_friendship_03.wem"
        },
        "189106a8c0f15fbf": {
            "hash": "189106a8c0f15fbf",
            "directory": "External3",
            "voiceContent": "SF",
            "sourceName": "vo_kaeya_battle_attacklight_07.wem"
        },
        "19034ccb85cbfff4": {
            "hash": "19034ccb85cbfff4",
            "directory": "External3",
            "voiceContent": "骑兵队长的头衔可没什么了不起的。说起来，蒙德城的骑兵都被大团长带走了。呵呵",
            "sourceName": "vo_kaeya_friendship_01.wem"
        },
        "19915da5c1cb0986": {
            "hash": "19915da5c1cb0986",
            "directory": "External3",
            "voiceContent": "配上美酒，会变得更美味吧",
            "sourceName": "vo_kaeya_spice_normal_01.wem"
        },
        "1c45de2a564af5dc": {
            "hash": "1c45de2a564af5dc",
            "directory": "External3",
            "voiceContent": "抱歉哦",
            "sourceName": "vo_kaeya_battle_skill3_02.wem"
        },
        "1dbcf32c03177d1a": {
            "hash": "1dbcf32c03177d1a",
            "directory": "External3",
            "voiceContent": "你喜欢酒吗？蒲公英酒的口感就很特别。什么？还没到喝酒的年纪？呵呵，那试一试蒙德的苹果酿吧，我知道一家还算不错的店",
            "sourceName": "vo_kaeya_dialog_share.wem"
        },
        "1e07078cce7b8124": {
            "hash": "1e07078cce7b8124",
            "directory": "External3",
            "voiceContent": "侦察骑士是个机灵又正义的好骑士。可千万别在她面前做坏事喔",
            "sourceName": "vo_kaeya_teammate_ambor_01.wem"
        },
        "1e50549d09b28568": {
            "hash": "1e50549d09b28568",
            "directory": "External3",
            "voiceContent": "品酒也是一种艺术，蒙德的酒是风神的恩赐，懂得好好品味才不会浪费了这份幸运",
            "sourceName": "vo_kaeya_pref_hobby.wem"
        },
        "2080bf79e696fd93": {
            "hash": "2080bf79e696fd93",
            "directory": "External4",
            "voiceContent": "蒙德特酿的起泡白葡萄酒，兑上三份蒲公英酒，苦味会被完美中和，这种酒名叫「午后之死」。美味",
            "sourceName": "vo_kaeya_pref_foodLike.wem"
        },
        "20f1f7a49f7e9162": {
            "hash": "20f1f7a49f7e9162",
            "directory": "External4",
            "voiceContent": "配上美酒，会变得更美味吧",
            "sourceName": "vo_kaeya_spice_event_normal_01.wem"
        },
        "22974e6a210f0471": {
            "hash": "22974e6a210f0471",
            "directory": "External4",
            "voiceContent": "哦？代理团长大人，你可要多多支持她",
            "sourceName": "vo_kaeya_teammate_qin_01.wem"
        },
        "297dd9e4cc29ea84": {
            "hash": "297dd9e4cc29ea84",
            "directory": "External5",
            "voiceContent": "不愧是你，真是技高一筹啊",
            "sourceName": "vo_card_kaeya_endOfGame_fail_01.wem"
        },
        "2bafe5aab405c0d7": {
            "hash": "2bafe5aab405c0d7",
            "directory": "External5",
            "voiceContent": "SF",
            "sourceName": "vo_kaeya_battle_hit_l_01.wem"
        },
        "2cd9d1bc5e87bef1": {
            "hash": "2cd9d1bc5e87bef1",
            "directory": "External5",
            "voiceContent": "SF",
            "sourceName": "vo_kaeya_battle_hit_l_03.wem"
        },
        "2fad675e3650565b": {
            "hash": "2fad675e3650565b",
            "directory": "External5",
            "voiceContent": "真是急性子啊你",
            "sourceName": "vo_kaeya_explore_sprint_start_01.wem"
        },
        "31009adbca542472": {
            "hash": "31009adbca542472",
            "directory": "External6",
            "voiceContent": "丽莎啊…你千万记得要准时还书哦？上次因为这事儿惹她生了气，直到现在我左手的尺骨还是麻麻的",
            "sourceName": "vo_kaeya_teammate_lisa_01.wem"
        },
        "343c536fe3b3ca75": {
            "hash": "343c536fe3b3ca75",
            "directory": "External6",
            "voiceContent": "SF",
            "sourceName": "vo_kaeya_explore_sprint_start_03.wem"
        },
        "3571b71e1899f800": {
            "hash": "3571b71e1899f800",
            "directory": "External6",
            "voiceContent": "SF",
            "sourceName": "vo_kaeya_explore_jump_05.wem"
        },
        "35e820e8518792a3": {
            "hash": "35e820e8518792a3",
            "directory": "External6",
            "voiceContent": "看来该认真了",
            "sourceName": "vo_kaeya_life_less30_01.wem"
        },
        "372315aaa5c72184": {
            "hash": "372315aaa5c72184",
            "directory": "External6",
            "voiceContent": "SF",
            "sourceName": "vo_kaeya_battle_attackheavy_03.wem"
        },
        "3782e7b4f800d6bf": {
            "hash": "3782e7b4f800d6bf",
            "directory": "External6",
            "voiceContent": "骑士团的战友们已经忙得不可开交了吧，哼哼",
            "sourceName": "vo_kaeya_explore_idle_02.wem"
        },
        "37be043f62324e6c": {
            "hash": "37be043f62324e6c",
            "directory": "External6",
            "voiceContent": "真是和平啊，可又能持续多久呢",
            "sourceName": "vo_kaeya_weather_breezy_01.wem"
        },
        "391a26e38b7e8339": {
            "hash": "391a26e38b7e8339",
            "directory": "External7",
            "voiceContent": "坎瑞亚？哦，你知道的真多。坎瑞亚的荣耀早已不在，剩下的如今都已沦为罪人，又何必再提起他们",
            "sourceName": "vo_kaeya_friendship_04.wem"
        },
        "3a5f65a2818c09ca": {
            "hash": "3a5f65a2818c09ca",
            "directory": "External7",
            "voiceContent": "这下刺激起来喽",
            "sourceName": "vo_card_kaeya_inGame_hard_03.wem"
        },
        "3d7f353e14bf1127": {
            "hash": "3d7f353e14bf1127",
            "directory": "External7",
            "voiceContent": "SF",
            "sourceName": "vo_kaeya_battle_hit_h_05.wem"
        },
        "4064fe8d1583160a": {
            "hash": "4064fe8d1583160a",
            "directory": "External8",
            "voiceContent": "SF",
            "sourceName": "vo_kaeya_explore_fly_start_03.wem"
        },
        "40c382bcf8c84e95": {
            "hash": "40c382bcf8c84e95",
            "directory": "External8",
            "voiceContent": "不明白「神之眼」的原理？嗯…我想想，给你打个比方吧。引导视线的器官是眼睛，而引导元素力的器官是「神之眼」。这样就很简单了吧",
            "sourceName": "vo_kaeya_dialog_pendant.wem"
        },
        "40ed3f25de3486ac": {
            "hash": "40ed3f25de3486ac",
            "directory": "External8",
            "voiceContent": "哦！这味道好棒，看不出来，你真有两下子啊",
            "sourceName": "vo_kaeya_spice_pref_01.wem"
        },
        "469bba2407be0bc9": {
            "hash": "469bba2407be0bc9",
            "directory": "External8",
            "voiceContent": "SF",
            "sourceName": "vo_kaeya_explore_idle_02.wem"
        },
        "49766d5be4212a29": {
            "hash": "49766d5be4212a29",
            "directory": "External9",
            "voiceContent": "真期待啊",
            "sourceName": "vo_kaeya_teamJoin_01.wem"
        },
        "4984bf9ca43485ae": {
            "hash": "4984bf9ca43485ae",
            "directory": "External9",
            "voiceContent": "冻结吧",
            "sourceName": "vo_kaeya_battle_skill1_02.wem"
        },
        "4a80af05deff5aa0": {
            "hash": "4a80af05deff5aa0",
            "directory": "External9",
            "voiceContent": "哎哟，我都有点不好意思了",
            "sourceName": "vo_card_kaeya_invite_easy_02.wem"
        },
        "4ab639cba507ce98": {
            "hash": "4ab639cba507ce98",
            "directory": "External9",
            "voiceContent": "阿贝多啊，沉稳优雅的小帅哥，而且才华横溢，是很讨人喜欢的类型。怎么，你也心动了",
            "sourceName": "vo_kaeya_teammate_albedo_01.wem"
        },
        "4d98551b5a632513": {
            "hash": "4d98551b5a632513",
            "directory": "External9",
            "voiceContent": "可恶",
            "sourceName": "vo_kaeya_battle_hit_H_01.wem"
        },
        "4dc7459ba587ef8b": {
            "hash": "4dc7459ba587ef8b",
            "directory": "External9",
            "voiceContent": "SF",
            "sourceName": "vo_kaeya_explore_climb_05.wem"
        },
        "4ec2412d04e5230d": {
            "hash": "4ec2412d04e5230d",
            "directory": "External9",
            "voiceContent": "SF",
            "sourceName": "vo_kaeya_battle_hit_h_03.wem"
        },
        "519269b4c9c7063c": {
            "hash": "519269b4c9c7063c",
            "directory": "External10",
            "voiceContent": "哦唷，你要先让我一张吗",
            "sourceName": "vo_card_kaeya_inGame_hard_01.wem"
        },
        "559d9cde40c7e6c8": {
            "hash": "559d9cde40c7e6c8",
            "directory": "External10",
            "voiceContent": "你也尝过了迪奥娜调的酒？还没到喝酒的年纪呐。哈哈，哎呀，可惜，真是可惜，这种快乐无法跟你共享。呵呵，只能期待你早点长大喽",
            "sourceName": "vo_kaeya_teammate_diona_01.wem"
        },
        "55e278c0d5a887b8": {
            "hash": "55e278c0d5a887b8",
            "directory": "External10",
            "voiceContent": "SF",
            "sourceName": "vo_kaeya_battle_attacklight_04.wem"
        },
        "55f1c1a4cdad84e0": {
            "hash": "55f1c1a4cdad84e0",
            "directory": "External10",
            "voiceContent": "SF",
            "sourceName": "vo_kaeya_battle_attackmid_02.wem"
        },
        "571e64da3b679a0e": {
            "hash": "571e64da3b679a0e",
            "directory": "External10",
            "voiceContent": "输掉喽，我还真是技不如人呐",
            "sourceName": "vo_card_kaeya_invite_hard_03.wem"
        },
        "584858ebe5e9a5b0": {
            "hash": "584858ebe5e9a5b0",
            "directory": "External11",
            "voiceContent": "我早等着你来找我打牌呢",
            "sourceName": "vo_card_kaeya_invite_hard_01.wem"
        },
        "5afd029f609f897c": {
            "hash": "5afd029f609f897c",
            "directory": "External11",
            "voiceContent": "起风了",
            "sourceName": "vo_kaeya_explore_fly_start_01.wem"
        },
        "5b56b8949f37ba0c": {
            "hash": "5b56b8949f37ba0c",
            "directory": "External11",
            "voiceContent": "说来可惜，现在的西风骑士团里，根本没人继承大团长的行事作风。唉…我个人倒还挺欣赏那种的",
            "sourceName": "vo_kaeya_teammate_varka_01.wem"
        },
        "5b9fe3cc31c01081": {
            "hash": "5b9fe3cc31c01081",
            "directory": "External11",
            "voiceContent": "打牌嘛，就要出其不意",
            "sourceName": "vo_card_kaeya_inGame_hard_04.wem"
        },
        "5d883b111bd0f018": {
            "hash": "5d883b111bd0f018",
            "directory": "External11",
            "voiceContent": "哎呀，只能说刚刚那把，运气站在我这边",
            "sourceName": "vo_card_kaeya_endOfGame_win_01.wem"
        },
        "5e55a14ad75838af": {
            "hash": "5e55a14ad75838af",
            "directory": "External11",
            "voiceContent": "早就准备好喽",
            "sourceName": "vo_kaeya_teamJoin_03.wem"
        },
        "5eb585875d68fb86": {
            "hash": "5eb585875d68fb86",
            "directory": "External11",
            "voiceContent": "SF",
            "sourceName": "vo_kaeya_explore_sprint_start_04.wem"
        },
        "5f19f2789e454d5e": {
            "hash": "5f19f2789e454d5e",
            "directory": "External11",
            "voiceContent": "什么？你说菲谢尔遮起一只眼睛的神秘样子，的确很符合「断罪皇女」的形象？哈哈哈，按照这个规律，我至少也得是个末代皇族后裔，对吧",
            "sourceName": "vo_kaeya_teammate_fischl_01.wem"
        },
        "5fda3dd109beeb6e": {
            "hash": "5fda3dd109beeb6e",
            "directory": "External11",
            "voiceContent": "放心，我只是吃得慢了一点，我会好好吃完的",
            "sourceName": "vo_kaeya_spice_event_dislike_01.wem"
        },
        "602b7b73a63bffa4": {
            "hash": "602b7b73a63bffa4",
            "directory": "External12",
            "voiceContent": "享受这一天吧",
            "sourceName": "vo_kaeya_dialog_greetingMorning.wem"
        },
        "603aed2ec932174a": {
            "hash": "603aed2ec932174a",
            "directory": "External12",
            "voiceContent": "让我帮你吧，记得欠我一个人情",
            "sourceName": "vo_kaeya_life_less30_teammate_01.wem"
        },
        "61a47cb6c5b56ac1": {
            "hash": "61a47cb6c5b56ac1",
            "directory": "External12",
            "voiceContent": "SF",
            "sourceName": "vo_kaeya_explore_fly_start_04.wem"
        },
        "64744589323711c3": {
            "hash": "64744589323711c3",
            "directory": "External12",
            "voiceContent": "SF",
            "sourceName": "vo_kaeya_battle_hit_l_05.wem"
        },
        "67cb8687dd388f6b": {
            "hash": "67cb8687dd388f6b",
            "directory": "External12",
            "voiceContent": "SF",
            "sourceName": "vo_kaeya_battle_attacklight_03.wem"
        },
        "6ac1a4afc8df88d6": {
            "hash": "6ac1a4afc8df88d6",
            "directory": "External13",
            "voiceContent": "SF",
            "sourceName": "vo_kaeya_battle_attacklight_06.wem"
        },
        "6d4312eaec78654a": {
            "hash": "6d4312eaec78654a",
            "directory": "External13",
            "voiceContent": "SF",
            "sourceName": "vo_kaeya_explore_jump_03.wem"
        },
        "6ddd362fabd8e45e": {
            "hash": "6ddd362fabd8e45e",
            "directory": "External13",
            "voiceContent": "怎么，你怕冷",
            "sourceName": "vo_kaeya_weather_snowy_02.wem"
        },
        "6e400020ffa820b9": {
            "hash": "6e400020ffa820b9",
            "directory": "External13",
            "voiceContent": "哦？既然这么在意我们之间的雇佣关系，就多使唤我一点吧，老大？哼哼，可别被我的真正实力吓到哦",
            "sourceName": "vo_kaeya_dialog_close2.wem"
        },
        "6f8aff8084858688": {
            "hash": "6f8aff8084858688",
            "directory": "External13",
            "voiceContent": "哦！这味道好棒，看不出来，你真有两下子啊",
            "sourceName": "vo_kaeya_spice_event_pref_01.wem"
        },
        "706cadbbac1fedd3": {
            "hash": "706cadbbac1fedd3",
            "directory": "External14",
            "voiceContent": "谢谢，那我不客气了",
            "sourceName": "vo_card_kaeya_inGame_easy_01.wem"
        },
        "71673faf076b6734": {
            "hash": "71673faf076b6734",
            "directory": "External14",
            "voiceContent": "啊哈哈，你想知道罗莎莉亚修女的秘密吗？这个不能说。不过我对她印象还不错，比某人好多了。她能够诚实地面对自己。烂事就是烂事，提不起干劲就是提不起干劲",
            "sourceName": "vo_kaeya_teammate_rosaria_01.wem"
        },
        "736f7300666c138c": {
            "hash": "736f7300666c138c",
            "directory": "External14",
            "voiceContent": "似乎变得无聊了",
            "sourceName": "vo_kaeya_life_less30_02.wem"
        },
        "74d459cd0cb7feb8": {
            "hash": "74d459cd0cb7feb8",
            "directory": "External14",
            "voiceContent": "没想到你也知道忙里偷闲",
            "sourceName": "vo_kaeya_explore_idle_01.wem"
        },
        "74fc99cd598514cd": {
            "hash": "74fc99cd598514cd",
            "directory": "External14",
            "voiceContent": "嚯…我都紧张地出汗了",
            "sourceName": "vo_card_kaeya_inGame_easy_03.wem"
        },
        "76313744ec843ffe": {
            "hash": "76313744ec843ffe",
            "directory": "External14",
            "voiceContent": "这雨天里，冰冻的力量会更强吧，有趣",
            "sourceName": "vo_kaeya_weather_heavyRain_01.wem"
        },
        "77ae8da397575951": {
            "hash": "77ae8da397575951",
            "directory": "External14",
            "voiceContent": "老实点",
            "sourceName": "vo_kaeya_battle_skill1_01.wem"
        },
        "7a53872aba5af230": {
            "hash": "7a53872aba5af230",
            "directory": "External15",
            "voiceContent": "你好像一直都很照顾我嘛。谢啦",
            "sourceName": "vo_kaeya_starUp_02.wem"
        },
        "7f32b0848b961999": {
            "hash": "7f32b0848b961999",
            "directory": "External15",
            "voiceContent": "值得庆贺的日子，祝你今天能得到真正的快乐",
            "sourceName": "vo_kaeya_pref_birthday.wem"
        },
        "81172902139e2c23": {
            "hash": "81172902139e2c23",
            "directory": "External16",
            "voiceContent": "我受代理团长大人所托，暗中照顾这位后辈。不过她很懂事，不需要我操太多心。真是令人欣慰",
            "sourceName": "vo_kaeya_teammate_noel_01.wem"
        },
        "847616fd34b361bc": {
            "hash": "847616fd34b361bc",
            "directory": "External16",
            "voiceContent": "SF",
            "sourceName": "vo_kaeya_explore_jump_01.wem"
        },
        "87c3f8217504416d": {
            "hash": "87c3f8217504416d",
            "directory": "External16",
            "voiceContent": "…这刹那，将是你的永恒",
            "sourceName": "vo_kaeya_battle_skill3_03.wem"
        },
        "8862f034ecc0cc3e": {
            "hash": "8862f034ecc0cc3e",
            "directory": "External17",
            "voiceContent": "你该不会怕黑吧？哦？那我…可找到新素材了",
            "sourceName": "vo_kaeya_dialog_greetingNight.wem"
        },
        "89b385bbffeeffd6": {
            "hash": "89b385bbffeeffd6",
            "directory": "External17",
            "voiceContent": "逗留够久了吧，再不活动活动筋骨，要长出蘑菇来了",
            "sourceName": "vo_kaeya_explore_idle_03.wem"
        },
        "8ab6719b6f441a32": {
            "hash": "8ab6719b6f441a32",
            "directory": "External17",
            "voiceContent": "SF",
            "sourceName": "vo_kaeya_battle_attackheavy_01.wem"
        },
        "8e8391149cac6c01": {
            "hash": "8e8391149cac6c01",
            "directory": "External17",
            "voiceContent": "SF",
            "sourceName": "vo_kaeya_explore_jump_04.wem"
        },
        "8fb093451cae801e": {
            "hash": "8fb093451cae801e",
            "directory": "External17",
            "voiceContent": "SF",
            "sourceName": "vo_kaeya_battle_hit_h_04.wem"
        },
        "909cb7d711f8f158": {
            "hash": "909cb7d711f8f158",
            "directory": "External18",
            "voiceContent": "SF",
            "sourceName": "vo_kaeya_explore_climb_02.wem"
        },
        "90d9c756c72f45c0": {
            "hash": "90d9c756c72f45c0",
            "directory": "External18",
            "voiceContent": "SF",
            "sourceName": "vo_kaeya_battle_hit_h_06.wem"
        },
        "91eecbf39c0397f0": {
            "hash": "91eecbf39c0397f0",
            "directory": "External18",
            "voiceContent": "哼，意料之外",
            "sourceName": "vo_kaeya_life_die_02.wem"
        },
        "969e83b805d1dde3": {
            "hash": "969e83b805d1dde3",
            "directory": "External18",
            "voiceContent": "刚开始接触那会儿，我看米卡容易紧张，就跟他开了一点无关痛痒的小玩笑。哪知他更紧张了，连笑都笑得很僵硬…最后还特意写信道歉。欸，这种单纯老实的品质，难道是施密特家族的遗传",
            "sourceName": "vo_kaeya_teammate_mika_01.wem"
        },
        "97db68aa3865fe63": {
            "hash": "97db68aa3865fe63",
            "directory": "External18",
            "voiceContent": "哎唷！早就看见你了，是想和我来上两局吗？那你可得手下留情啊",
            "sourceName": "vo_card_kaeya_freetalk_01.wem"
        },
        "98cc202b0fabd508": {
            "hash": "98cc202b0fabd508",
            "directory": "External19",
            "voiceContent": "SF",
            "sourceName": "vo_kaeya_explore_idle_03.wem"
        },
        "a443421a8e6c5f00": {
            "hash": "a443421a8e6c5f00",
            "directory": "External20",
            "voiceContent": "哟，要不要一起去酒馆坐坐",
            "sourceName": "vo_kaeya_dialog_greetingNoon.wem"
        },
        "a5a81fb1e0576360": {
            "hash": "a5a81fb1e0576360",
            "directory": "External20",
            "voiceContent": "现在气氛正好，别走啊。不然…我再请你杯喝的吧",
            "sourceName": "vo_card_kaeya_leave_01.wem"
        },
        "a66c723570239bad": {
            "hash": "a66c723570239bad",
            "directory": "External20",
            "voiceContent": "孤独？怎么会，现在不就有人在我身边唠叨么",
            "sourceName": "vo_kaeya_dialog_annoyed.wem"
        },
        "ab1c77c4a1e7a170": {
            "hash": "ab1c77c4a1e7a170",
            "directory": "External21",
            "voiceContent": "SF",
            "sourceName": "vo_kaeya_battle_hit_l_02.wem"
        },
        "ad77991c3a18d170": {
            "hash": "ad77991c3a18d170",
            "directory": "External21",
            "voiceContent": "可莉，看来还是没有掌握躲避代理团长检查的技巧啊，明明我已经点拨过她…哈哈，我说着玩玩的，你可别去揭发我哦",
            "sourceName": "vo_kaeya_teammate_klee_01.wem"
        },
        "b249197826e653e4": {
            "hash": "b249197826e653e4",
            "directory": "External22",
            "voiceContent": "SF",
            "sourceName": "vo_kaeya_explore_sprint_start_02.wem"
        },
        "b283ebe56e6995de": {
            "hash": "b283ebe56e6995de",
            "directory": "External22",
            "voiceContent": "这样会更有意思点",
            "sourceName": "vo_card_kaeya_inGame_easy_04.wem"
        },
        "b3f6ccebcbfb3cb8": {
            "hash": "b3f6ccebcbfb3cb8",
            "directory": "External22",
            "voiceContent": "原来我们已经相遇这么久了。跟你一起旅行，大概是我这辈子遇上的最有趣的事儿了，今后可别让我失望哦",
            "sourceName": "vo_kaeya_friendship_05.wem"
        },
        "b4f9881860842923": {
            "hash": "b4f9881860842923",
            "directory": "External22",
            "voiceContent": "别看砂糖文静又内向，据说，她在实验室里，收藏了很多特别的东西哦，很刺激，又很…露骨的那种。嗯？你问我？…我像是会偷看女孩子房间的人吗",
            "sourceName": "vo_kaeya_teammate_sucrose_01.wem"
        },
        "b7cd483244e506de": {
            "hash": "b7cd483244e506de",
            "directory": "External22",
            "voiceContent": "运气还不错",
            "sourceName": "vo_kaeya_chest_open_01.wem"
        },
        "b86ff7829c5c176e": {
            "hash": "b86ff7829c5c176e",
            "directory": "External23",
            "voiceContent": "西风骑士团，凯亚。请让我与你同行吧。比起团里的差事，还是做你的护卫要有趣得多",
            "sourceName": "vo_kaeya_draw_appear.wem"
        },
        "b9c6148ee4f90d22": {
            "hash": "b9c6148ee4f90d22",
            "directory": "External23",
            "voiceContent": "SF",
            "sourceName": "vo_kaeya_battle_attacklight_02.wem"
        },
        "bbe6979a3dfe53d3": {
            "hash": "bbe6979a3dfe53d3",
            "directory": "External23",
            "voiceContent": "咦？你还挺有头脑的",
            "sourceName": "vo_card_kaeya_inGame_hard_02.wem"
        },
        "bc000cc005b93bdd": {
            "hash": "bc000cc005b93bdd",
            "directory": "External23",
            "voiceContent": "居然有人直接把葡萄汁拿来喝，明明只需少许时日就能变成佳酿的…啧，真是不懂浪漫",
            "sourceName": "vo_kaeya_pref_foodDislike.wem"
        },
        "bc5d7c43f24aa780": {
            "hash": "bc5d7c43f24aa780",
            "directory": "External23",
            "voiceContent": "哈哈，真有乐子",
            "sourceName": "vo_kaeya_chest_open_03.wem"
        },
        "bc7c4fa26577c115": {
            "hash": "bc7c4fa26577c115",
            "directory": "External23",
            "voiceContent": "SF",
            "sourceName": "vo_kaeya_battle_attackheavy_02.wem"
        },
        "c5513084d4d6d613": {
            "hash": "c5513084d4d6d613",
            "directory": "External24",
            "voiceContent": "SF",
            "sourceName": "vo_kaeya_explore_fly_start_02.wem"
        },
        "c5dfdab2d38b446b": {
            "hash": "c5dfdab2d38b446b",
            "directory": "External24",
            "voiceContent": "其实西风骑士团一共有十位队长。但不是所有人都有队长级的实力",
            "sourceName": "vo_kaeya_friendship_02.wem"
        },
        "cb42219460d4b0b7": {
            "hash": "cb42219460d4b0b7",
            "directory": "External25",
            "voiceContent": "这个如何",
            "sourceName": "vo_kaeya_battle_skill1_03.wem"
        },
        "cb7f4437dd50f901": {
            "hash": "cb7f4437dd50f901",
            "directory": "External25",
            "voiceContent": "呼…趁着这雪天，跟你讲一个鬼故事吧",
            "sourceName": "vo_kaeya_weather_snowy_01.wem"
        },
        "d6578c1b3b71c666": {
            "hash": "d6578c1b3b71c666",
            "directory": "External26",
            "voiceContent": "SF",
            "sourceName": "vo_kaeya_explore_idle_01.wem"
        },
        "d8dbc6d1f807c517": {
            "hash": "d8dbc6d1f807c517",
            "directory": "External27",
            "voiceContent": "别这么沮丧嘛，我请你杯果汁怎么样",
            "sourceName": "vo_card_kaeya_invite_hard_02.wem"
        },
        "d9323f5317d4e4c6": {
            "hash": "d9323f5317d4e4c6",
            "directory": "External27",
            "voiceContent": "去找点乐子吧",
            "sourceName": "vo_kaeya_teamJoin_02.wem"
        },
        "db05d2b8952bce39": {
            "hash": "db05d2b8952bce39",
            "directory": "External27",
            "voiceContent": "SF",
            "sourceName": "vo_kaeya_battle_attacklight_05.wem"
        },
        "db588c123e834bf3": {
            "hash": "db588c123e834bf3",
            "directory": "External27",
            "voiceContent": "小心着凉",
            "sourceName": "vo_kaeya_battle_skill3_01.wem"
        },
        "de309c465918b8b6": {
            "hash": "de309c465918b8b6",
            "directory": "External27",
            "voiceContent": "这就要走了吗。那就下回见了，别让我等太久啊",
            "sourceName": "vo_kaeya_dialog_greetingNight2.wem"
        },
        "de3722f8c9ab77ba": {
            "hash": "de3722f8c9ab77ba",
            "directory": "External27",
            "voiceContent": "本来只是同行，没想到你居然为我做到这一步…看来我也必须好好回应你才行呢。继续我们的旅程吧，挚友，是时候认真起来了",
            "sourceName": "vo_kaeya_starUp_04.wem"
        },
        "e2538cf78808885d": {
            "hash": "e2538cf78808885d",
            "directory": "External28",
            "voiceContent": "麻烦的家伙",
            "sourceName": "vo_kaeya_life_less30_03.wem"
        },
        "e3442735e62bd87c": {
            "hash": "e3442735e62bd87c",
            "directory": "External28",
            "voiceContent": "适可而止",
            "sourceName": "vo_kaeya_battle_hit_H_02.wem"
        },
        "e6520b383309884d": {
            "hash": "e6520b383309884d",
            "directory": "External28",
            "voiceContent": "喂，命丢了可就不好玩了",
            "sourceName": "vo_kaeya_life_less30_teammate_02.wem"
        },
        "e65a79cf17fd5a6d": {
            "hash": "e65a79cf17fd5a6d",
            "directory": "External28",
            "voiceContent": "嗯，柯莱？真是个怀念的名字，你可找对人了！我来告诉你过去发生的事情吧，干脆从头说起——保证原汁原味",
            "sourceName": "vo_kaeya_teammate_collei_01.wem"
        },
        "eeca44e2a8eaaf53": {
            "hash": "eeca44e2a8eaaf53",
            "directory": "External29",
            "voiceContent": "SF",
            "sourceName": "vo_kaeya_explore_jump_02.wem"
        },
        "f1ec6b69d929ff24": {
            "hash": "f1ec6b69d929ff24",
            "directory": "External30",
            "voiceContent": "迪卢克？小时候的他挺可爱的。可如今却活在自己的世界里…总之是个无趣的家伙",
            "sourceName": "vo_kaeya_teammate_diluc_01.wem"
        },
        "f3c01ced29abfd07": {
            "hash": "f3c01ced29abfd07",
            "directory": "External30",
            "voiceContent": "想和我打牌？我求之不得呢",
            "sourceName": "vo_card_kaeya_invite_easy_01.wem"
        },
        "f47f53a52147c3c2": {
            "hash": "f47f53a52147c3c2",
            "directory": "External30",
            "voiceContent": "SF",
            "sourceName": "vo_kaeya_explore_climb_04.wem"
        },
        "f4e908fed42c4821": {
            "hash": "f4e908fed42c4821",
            "directory": "External30",
            "voiceContent": "哈哈哈，让你看笑话喽",
            "sourceName": "vo_card_kaeya_invite_easy_03.wem"
        },
        "f55a5e4eb39a1870": {
            "hash": "f55a5e4eb39a1870",
            "directory": "External30",
            "voiceContent": "你见过龙脊雪山的猫头鹰么？和它对视的时候，它好像看穿了你，而你却完全参不透它…很迷人的家伙，不是吗",
            "sourceName": "vo_kaeya_pref_gift.wem"
        },
        "fa2017a3bdffc42c": {
            "hash": "fa2017a3bdffc42c",
            "directory": "External31",
            "voiceContent": "SF",
            "sourceName": "vo_kaeya_battle_hit_l_06.wem"
        },
        "fae6f510cc791197": {
            "hash": "fae6f510cc791197",
            "directory": "External31",
            "voiceContent": "嚯，你也有两下子嘛",
            "sourceName": "vo_kaeya_starUp_01.wem"
        },
        "fb26c5bc865d97df": {
            "hash": "fb26c5bc865d97df",
            "directory": "External31",
            "voiceContent": "SF",
            "sourceName": "vo_kaeya_explore_climb_01.wem"
        },
        "fd5053a5fa1e1c5e": {
            "hash": "fd5053a5fa1e1c5e",
            "directory": "External31",
            "voiceContent": "呼，哈哈",
            "sourceName": "vo_kaeya_explore_sprint_end_01.wem"
        },
        "fdfbd218335bdb56": {
            "hash": "fdfbd218335bdb56",
            "directory": "External31",
            "voiceContent": "需要我的时候就派我上场吧，别谈那些雇佣关系了",
            "sourceName": "vo_kaeya_dialog_close1.wem"
        },
        "ff312f8c185a2747": {
            "hash": "ff312f8c185a2747",
            "directory": "External31",
            "voiceContent": "SF",
            "sourceName": "vo_kaeya_battle_attackmid_01.wem"
        },
        "ff3ffd82e5603589": {
            "hash": "ff3ffd82e5603589",
            "directory": "External31",
            "voiceContent": "你最近有没有被深渊教团找麻烦？有什么心烦的可以跟我聊聊",
            "sourceName": "vo_kaeya_dialog_idle.wem"
        },
        "ff76e12279de38b1": {
            "hash": "ff76e12279de38b1",
            "directory": "External31",
            "voiceContent": "力量又增强了啊…我说，你那是什么眼神，怎么感觉比我还兴奋",
            "sourceName": "vo_kaeya_starUp_03.wem"
        }
    }
}