{
    "Teapot": {},
    "Quests": {
        "05d60bddf73312c5": {
            "hash": "05d60bddf73312c5",
            "directory": "External0",
            "voiceContent": "#Hey, stop running around! You're blocking h{M#is}{F#er} way",
            "sourceName": "vo_NTAQ303_10_kachina_01a.wem"
        },
        "12c1e90de5e0e30f": {
            "hash": "12c1e90de5e0e30f",
            "directory": "External2",
            "voiceContent": "I'm fine, I'm fine! You should know I'm made of stronger stuff than that",
            "sourceName": "vo_NTAQ007_7_kachina_12.wem"
        },
        "193a4dbb59923f7c": {
            "hash": "193a4dbb59923f7c",
            "directory": "External3",
            "voiceContent": "Watch out for the falling rocks",
            "sourceName": "vo_NTAQ007_9_kachina_13.wem"
        },
        "2262e2ac0255c5d4": {
            "hash": "2262e2ac0255c5d4",
            "directory": "External4",
            "voiceContent": "Phew..",
            "sourceName": "vo_NTAQ002_4_kachina_08.wem"
        },
        "302380f86a0149e7": {
            "hash": "302380f86a0149e7",
            "directory": "External6",
            "voiceContent": "*panting*... Yep, all good. C'mon, let's head back to the Stadium..",
            "sourceName": "vo_NTAQ002_4_kachina_07.wem"
        },
        "302985a8e0978566": {
            "hash": "302985a8e0978566",
            "directory": "External6",
            "voiceContent": "That was close..",
            "sourceName": "vo_NTAQ002_6_kachina_08.wem"
        },
        "30deaca235e2e46e": {
            "hash": "30deaca235e2e46e",
            "directory": "External6",
            "voiceContent": "We...? Aww, is that also a compliment towards me? ...Hehe, yeah, we ARE unstoppable",
            "sourceName": "vo_NTAQ108_4_kachina_03.wem"
        },
        "3cbc77f0b8265acc": {
            "hash": "3cbc77f0b8265acc",
            "directory": "External7",
            "voiceContent": "My parents wanted me to learn dance, but I wanted to become a warrior instead",
            "sourceName": "vo_NTAQ001_4_kachina_05.wem"
        },
        "3de6640262a858ee": {
            "hash": "3de6640262a858ee",
            "directory": "External7",
            "voiceContent": "Many of our tribespeople love music and dance, and have an amazing sense of rhythm",
            "sourceName": "vo_NTAQ001_4_kachina_03.wem"
        },
        "3ef380baa89b3a63": {
            "hash": "3ef380baa89b3a63",
            "directory": "External7",
            "voiceContent": "I'm fine. I don't scare easily, not after that last ride you took me on",
            "sourceName": "vo_NTAQ002_4_kachina_10.wem"
        },
        "403ca0d5afa55dd3": {
            "hash": "403ca0d5afa55dd3",
            "directory": "External8",
            "voiceContent": "W—We actually beat a legend..",
            "sourceName": "vo_NTAQ002_4_kachina_03.wem"
        },
        "44cc8ce75d0a84cd": {
            "hash": "44cc8ce75d0a84cd",
            "directory": "External8",
            "voiceContent": "W—We won",
            "sourceName": "vo_NTAQ002_4_kachina_01.wem"
        },
        "4cd957c0e3651f43": {
            "hash": "4cd957c0e3651f43",
            "directory": "External9",
            "voiceContent": "(Wait, maybe I can try climbing that stone pillar! I should be able to catch her that way!",
            "sourceName": "vo_NTAQ002_6_kachina_05.wem"
        },
        "516943d290ca467d": {
            "hash": "516943d290ca467d",
            "directory": "External10",
            "voiceContent": "(It's not just about who hits the hardest!",
            "sourceName": "vo_NTAQ002_6_kachina_07.wem"
        },
        "8253deff71ef05de": {
            "hash": "8253deff71ef05de",
            "directory": "External16",
            "voiceContent": "They're going at it! What's our play, Mualani",
            "sourceName": "vo_NTAQ002_4_kachina_06.wem"
        },
        "82aa098c7ca6182b": {
            "hash": "82aa098c7ca6182b",
            "directory": "External16",
            "voiceContent": "#Look over here, {NICKNAME}",
            "sourceName": "vo_NTAQ303_18_iansan_01.wem"
        },
        "82c3df591dbd3709": {
            "hash": "82c3df591dbd3709",
            "directory": "External16",
            "voiceContent": "She's really freaking out! What's going on",
            "sourceName": "vo_NTAQ301_22_kachina_05.wem"
        },
        "86e413111f54a680": {
            "hash": "86e413111f54a680",
            "directory": "External16",
            "voiceContent": "Just leave it to me! I'll get us up there",
            "sourceName": "vo_NTAQ002_4_kachina_04.wem"
        },
        "915acec1b0b81d1a": {
            "hash": "915acec1b0b81d1a",
            "directory": "External18",
            "voiceContent": "Actually, I was feeling pretty down that day. My training didn't go well, and... Anyway, you really cheered me up",
            "sourceName": "vo_NTAQ002_4_kachina_11.wem"
        },
        "ab64edd5c8722ea2": {
            "hash": "ab64edd5c8722ea2",
            "directory": "External21",
            "voiceContent": "#Hey, stop running around! You're blocking h{M#is}{F#er} way",
            "sourceName": "vo_NTAQ303_10_kachina_01b.wem"
        },
        "aba091e7d9c2ce9d": {
            "hash": "aba091e7d9c2ce9d",
            "directory": "External21",
            "voiceContent": "In the past, outlanders have come here just to study our culture and exchange views",
            "sourceName": "vo_NTAQ001_4_kachina_04.wem"
        },
        "b6020e99f5663877": {
            "hash": "b6020e99f5663877",
            "directory": "External22",
            "voiceContent": "Now it's my turn. Go, Turbo Twirly",
            "sourceName": "vo_NTAQ108_4_kachina_02.wem"
        },
        "beb56eddf33313ca": {
            "hash": "beb56eddf33313ca",
            "directory": "External23",
            "voiceContent": "How did these monsters make it onto the grounds..",
            "sourceName": "vo_NTAQ002_4_kachina_02.wem"
        },
        "c309c5fa222bacf7": {
            "hash": "c309c5fa222bacf7",
            "directory": "External24",
            "voiceContent": "It's not going anywhere, I promise you",
            "sourceName": "vo_NTAQ001_4_kachina_02.wem"
        },
        "cd019ca4f7b0e5a5": {
            "hash": "cd019ca4f7b0e5a5",
            "directory": "External25",
            "voiceContent": "Thanks, Mualani",
            "sourceName": "vo_NTAQ002_4_kachina_09.wem"
        },
        "dff5ed07a3671a81": {
            "hash": "dff5ed07a3671a81",
            "directory": "External27",
            "voiceContent": "Hehe, glad I could help",
            "sourceName": "vo_NTAQ002_4_kachina_05.wem"
        },
        "e0b020b16f470f90": {
            "hash": "e0b020b16f470f90",
            "directory": "External28",
            "voiceContent": "Wheeeeee! This is just like riding a Spiritway",
            "sourceName": "vo_NTAQ108_4_kachina_01.wem"
        },
        "e28529db6f2dd1ac": {
            "hash": "e28529db6f2dd1ac",
            "directory": "External28",
            "voiceContent": "(She's strong. I can't rush this. Just like the Traveler said, I need to observe my opponent and look for an opportunity...",
            "sourceName": "vo_NTAQ002_6_kachina_06.wem"
        },
        "edb7d8119c0c8410": {
            "hash": "edb7d8119c0c8410",
            "directory": "External29",
            "voiceContent": "Hahaha, don't worry! Our tribe works closely with stone. That's one of our symbols, actually",
            "sourceName": "vo_NTAQ001_4_kachina_01.wem"
        },
        "eec5ecc9e2010b1d": {
            "hash": "eec5ecc9e2010b1d",
            "directory": "External29",
            "voiceContent": "Mualani, I... I really want to win this time. I want to win this Pilgrimage and become a true warrior",
            "sourceName": "vo_NTAQ002_4_kachina_12.wem"
        },
        "f76425ca6264817a": {
            "hash": "f76425ca6264817a",
            "directory": "External30",
            "voiceContent": "(I've got to turn this around, and fast...",
            "sourceName": "vo_NTAQ002_6_kachina_04.wem"
        }
    },
    "Gameplay": {
        "0692cd21a8ce84fa": {
            "hash": "0692cd21a8ce84fa",
            "directory": "External0",
            "voiceContent": "She's a famous peacemaker in Natlan! They say she can resolve any conflict, no sweat. I guess that she probably does it because like me, she's really not a fan of people getting into fights with each other..",
            "sourceName": "vo_kachina_teammate_chasca_01.wem"
        },
        "08f4cc34d2855bfa": {
            "hash": "08f4cc34d2855bfa",
            "directory": "External1",
            "voiceContent": "Hello! I'm Kachina, a member of the Children of Echoes. I adore Grainfruits and would love to become more strong, even though I'm still not much of a fighter. Uh... I should probably save all that for later, right? Then, um... Are you hoping to go somewhere? I'm pretty familiar with these parts, so I can show you the way",
            "sourceName": "vo_kachina_draw_appear_01.wem"
        },
        "096a55223582de9a": {
            "hash": "096a55223582de9a",
            "directory": "External1",
            "voiceContent": "You've shown me all kinds of new and fascinating things, and really helped me to grow... I have no idea how I could ever repay you, but I want to find the answer by myself. So from now on, please allow me to be the hero... the hero that protects you",
            "sourceName": "vo_kachina_starUp_04.wem"
        },
        "0e0d3b18b4da595d": {
            "hash": "0e0d3b18b4da595d",
            "directory": "External1",
            "voiceContent": "SFX",
            "sourceName": "vo_kachina_battle_attacklight_01.wem"
        },
        "0f8df6d037f80873": {
            "hash": "0f8df6d037f80873",
            "directory": "External1",
            "voiceContent": "I love Grainfruit Chips! I would love them even more if they could be stacked neatly into a tower",
            "sourceName": "vo_kachina_pref_foodLike.wem"
        },
        "0f90524d6cc90064": {
            "hash": "0f90524d6cc90064",
            "directory": "External1",
            "voiceContent": "Drilling down",
            "sourceName": "vo_kachina_battle_skill3_02.wem"
        },
        "0f93c7acd4bfbfd4": {
            "hash": "0f93c7acd4bfbfd4",
            "directory": "External1",
            "voiceContent": "Spin to win",
            "sourceName": "vo_kachina_battle_skill1_04.wem"
        },
        "10bcf3be7f407736": {
            "hash": "10bcf3be7f407736",
            "directory": "External2",
            "voiceContent": "Sha~bam",
            "sourceName": "vo_kachina_battle_skill1_02.wem"
        },
        "157ba4cd749fb541": {
            "hash": "157ba4cd749fb541",
            "directory": "External2",
            "voiceContent": "SFX",
            "sourceName": "vo_kachina_explore_idle_02.wem"
        },
        "19206f9b958a42c9": {
            "hash": "19206f9b958a42c9",
            "directory": "External3",
            "voiceContent": "No... I messed up... again..",
            "sourceName": "vo_kachina_life_die_03.wem"
        },
        "19edbb8f6edef292": {
            "hash": "19edbb8f6edef292",
            "directory": "External3",
            "voiceContent": "Do you think there's any shiny ores underneath all of this sand? We can do a quick dig just to check",
            "sourceName": "vo_kachina_weather_desert_01.wem"
        },
        "1bd5bb01f59eacd8": {
            "hash": "1bd5bb01f59eacd8",
            "directory": "External3",
            "voiceContent": "Need help organizing the loot? I'm an expert",
            "sourceName": "vo_kachina_chest_open_03.wem"
        },
        "1ca26405f7ef149e": {
            "hash": "1ca26405f7ef149e",
            "directory": "External3",
            "voiceContent": "Mualani asked me to go into a cave with her tonight in a test of courage, and I—I—I'm... I'm so scared! What should I do? I didn't want to disappoint her, so I closed my eyes and said I'd go... No matter what happens, I should face it together with her! Ehh!? You're coming too? Th—Thank goodness! Phew..",
            "sourceName": "vo_kachina_dialog_greetingNight.wem"
        },
        "23a5c2f2efdd51cc": {
            "hash": "23a5c2f2efdd51cc",
            "directory": "External4",
            "voiceContent": "SFX",
            "sourceName": "vo_kachina_explore_sprint_start_02.wem"
        },
        "25766f2afd4336b7": {
            "hash": "25766f2afd4336b7",
            "directory": "External4",
            "voiceContent": "SFX",
            "sourceName": "vo_kachina_battle_attacklight_07.wem"
        },
        "285fb7779d397f3d": {
            "hash": "285fb7779d397f3d",
            "directory": "External5",
            "voiceContent": "Huh!? Is this really just one portion? But if I don't finish the whole thing, won't I have let the chef's hard work go to waste? I—It's alright, I'll finish the whole thing! Small bites, Kachina, small bites..",
            "sourceName": "vo_kachina_pref_foodDislike.wem"
        },
        "2912a2179b85b8c8": {
            "hash": "2912a2179b85b8c8",
            "directory": "External5",
            "voiceContent": "It's just a scratch",
            "sourceName": "vo_kachina_battle_hit_L_02.wem"
        },
        "294b1da0709dea04": {
            "hash": "294b1da0709dea04",
            "directory": "External5",
            "voiceContent": "Good morning! I've already packed everything, so we can head out whenever",
            "sourceName": "vo_kachina_dialog_greetingMorning.wem"
        },
        "2a99a38a85de284f": {
            "hash": "2a99a38a85de284f",
            "directory": "External5",
            "voiceContent": "Sorry... I pushed myself... too hard",
            "sourceName": "vo_kachina_life_die_01.wem"
        },
        "2aaa134be5b59f91": {
            "hash": "2aaa134be5b59f91",
            "directory": "External5",
            "voiceContent": "Though the court burned to rubble, the flame never once went out. It shall reignite the next morn, more radiant than afore. This is one of my favorite quotes from Lord Traore. I—I must keep working hard",
            "sourceName": "vo_kachina_starUp_03.wem"
        },
        "2d14a04d684a63e3": {
            "hash": "2d14a04d684a63e3",
            "directory": "External5",
            "voiceContent": "I can do it... No, I can't... I can do it... No, I... Ahem, it's fine, I can definitely do it!!! ...Right",
            "sourceName": "vo_kachina_character_idle_02.wem"
        },
        "2ddceac4a2c61826": {
            "hash": "2ddceac4a2c61826",
            "directory": "External5",
            "voiceContent": "The taste, the aroma, the presentation... everything about this dish is marvelous! If there's ever a cook-off, I'm sure you'd win",
            "sourceName": "vo_kachina_spice_normal_01.wem"
        },
        "2e5aa1109e684624": {
            "hash": "2e5aa1109e684624",
            "directory": "External5",
            "voiceContent": "Oh yay! Okay, let's go",
            "sourceName": "vo_kachina_teamJoin_02.wem"
        },
        "30b4e6f0e8d5adf6": {
            "hash": "30b4e6f0e8d5adf6",
            "directory": "External6",
            "voiceContent": "Whoa! Look at all these shiny rocks",
            "sourceName": "vo_kachina_chest_open_01.wem"
        },
        "3181a17f1448c034": {
            "hash": "3181a17f1448c034",
            "directory": "External6",
            "voiceContent": "Oof... I'm fine",
            "sourceName": "vo_kachina_battle_hit_H_02.wem"
        },
        "3258926ae1e8a030": {
            "hash": "3258926ae1e8a030",
            "directory": "External6",
            "voiceContent": "SFX",
            "sourceName": "vo_kachina_explore_climb_02.wem"
        },
        "3794efdea03150fb": {
            "hash": "3794efdea03150fb",
            "directory": "External6",
            "voiceContent": "SFX",
            "sourceName": "vo_kachina_battle_hit_l_05.wem"
        },
        "3a68b597628ae0c7": {
            "hash": "3a68b597628ae0c7",
            "directory": "External7",
            "voiceContent": "Ifa's a really amazing sauro-vet! Any little Saurian who sees him comes back and starts living a healthy life! They eat right, sleep well, don't cause trouble, and basically don't get sick again! So whenever a Saurian's looking sick, everyone's first thought is to ask him to fly over and have a look",
            "sourceName": "vo_kachina_teammate_ifa_01.wem"
        },
        "400e2833b4757a18": {
            "hash": "400e2833b4757a18",
            "directory": "External8",
            "voiceContent": "I've always thought that it was only natural for me to be overlooked because I was weak. Now that I've talked with the Wayob though, I've changed my mind. Uthabiti is my Ancient Name, and I've... I've decided to become the best me I can be. There have to be things in this world that only I can accomplish. I will... keep striving. I hope this obsidian will one day hold a record of my deeds and become... even more radiant and dazzling",
            "sourceName": "vo_kachina_friendship_05.wem"
        },
        "45e30b9afc37f82b": {
            "hash": "45e30b9afc37f82b",
            "directory": "External8",
            "voiceContent": "SFX",
            "sourceName": "vo_kachina_explore_fly_start_02.wem"
        },
        "4806168e84c0b1cb": {
            "hash": "4806168e84c0b1cb",
            "directory": "External9",
            "voiceContent": "It's nothing, I can walk it off",
            "sourceName": "vo_kachina_life_less30_01.wem"
        },
        "492f42a02f416925": {
            "hash": "492f42a02f416925",
            "directory": "External9",
            "voiceContent": "I... I can do it! I have to",
            "sourceName": "vo_kachina_life_less30_03.wem"
        },
        "4ad6d95b6aa1b0e9": {
            "hash": "4ad6d95b6aa1b0e9",
            "directory": "External9",
            "voiceContent": "SFX",
            "sourceName": "vo_kachina_battle_attackmid_03.wem"
        },
        "4d1d7cf185df4222": {
            "hash": "4d1d7cf185df4222",
            "directory": "External9",
            "voiceContent": "SFX",
            "sourceName": "vo_kachina_explore_jump_03.wem"
        },
        "4d4ac2e311d56dec": {
            "hash": "4d4ac2e311d56dec",
            "directory": "External9",
            "voiceContent": "SFX",
            "sourceName": "vo_kachina_battle_attackheavy_03.wem"
        },
        "4e466103305f7ff4": {
            "hash": "4e466103305f7ff4",
            "directory": "External9",
            "voiceContent": "SFX",
            "sourceName": "vo_kachina_explore_jump_01.wem"
        },
        "502581427725c1d0": {
            "hash": "502581427725c1d0",
            "directory": "External10",
            "voiceContent": "SFX",
            "sourceName": "vo_kachina_battle_attacklight_04.wem"
        },
        "505e2810fa489ad4": {
            "hash": "505e2810fa489ad4",
            "directory": "External10",
            "voiceContent": "Uthabiti is my Ancient Name — it means the ability to stay strong in the face of adversity. *sigh* But I often wonder why the Wayob decided to give the name to me. I'm so weak, and whether at home or among the tribe, few people even know of me... With so many strong and cool people around me, am I really worthy of the name",
            "sourceName": "vo_kachina_friendship_01.wem"
        },
        "5c500d4a5af5966f": {
            "hash": "5c500d4a5af5966f",
            "directory": "External11",
            "voiceContent": "SFX",
            "sourceName": "vo_kachina_battle_attackmid_01.wem"
        },
        "5ec3bed20228f3ba": {
            "hash": "5ec3bed20228f3ba",
            "directory": "External11",
            "voiceContent": "SFX",
            "sourceName": "vo_kachina_battle_attackheavy_01.wem"
        },
        "5fc1639d9b59fb82": {
            "hash": "5fc1639d9b59fb82",
            "directory": "External11",
            "voiceContent": "Let's go, Twirly",
            "sourceName": "vo_kachina_battle_skill1_06.wem"
        },
        "61a1cf097e5963a3": {
            "hash": "61a1cf097e5963a3",
            "directory": "External12",
            "voiceContent": "SFX",
            "sourceName": "vo_kachina_battle_attacklight_03.wem"
        },
        "61d6eb6ffc60be16": {
            "hash": "61d6eb6ffc60be16",
            "directory": "External12",
            "voiceContent": "Ayo is a very important companion to me! Even though he looks well-behaved now, he really loved headbutting people when he was younger. He's super strong, so even I get knocked over sometimes. Not much you can do about it, though, because it's just how Tepetlisaurs show their affection! Oof, Ayo, stop headbutting me! Alright, alright, I won't say any more",
            "sourceName": "vo_kachina_dialog_share_01.wem"
        },
        "620e21f619e68204": {
            "hash": "620e21f619e68204",
            "directory": "External12",
            "voiceContent": "SFX",
            "sourceName": "vo_kachina_battle_hit_l_06.wem"
        },
        "69ced5b50352f89f": {
            "hash": "69ced5b50352f89f",
            "directory": "External13",
            "voiceContent": "Here goes",
            "sourceName": "vo_kachina_battle_skill1_03.wem"
        },
        "6b50d5a29d780c08": {
            "hash": "6b50d5a29d780c08",
            "directory": "External13",
            "voiceContent": "My name... I must honor it..",
            "sourceName": "vo_kachina_life_die_02.wem"
        },
        "6e02f2658013c0cc": {
            "hash": "6e02f2658013c0cc",
            "directory": "External13",
            "voiceContent": "Ah... I just saw a brick that wasn't properly stacked. What should I do? Now it feels like there's a little Saurian scratching away inside my chest..",
            "sourceName": "vo_kachina_character_idle_01.wem"
        },
        "6e5d3b1b36120339": {
            "hash": "6e5d3b1b36120339",
            "directory": "External13",
            "voiceContent": "SFX",
            "sourceName": "vo_kachina_explore_jump_04.wem"
        },
        "73c1fb33c7687315": {
            "hash": "73c1fb33c7687315",
            "directory": "External14",
            "voiceContent": "Aaah!! Um... I—I'm not scared! I was just... caught off guard",
            "sourceName": "vo_kachina_weather_thunder_01.wem"
        },
        "742ced07e966539b": {
            "hash": "742ced07e966539b",
            "directory": "External14",
            "voiceContent": "Falling in battle during the Night Warden Wars is an honor for the warriors of Natlan. As one of their number, I should feel the same. But while I was down there, even as I kept repeating that to myself, I was still terrified the whole time... I'm really grateful that you took such a huge risk to go to the Night Kingdom and bring me back... *sniffle* Really, I can't thank you enough",
            "sourceName": "vo_kachina_dialog_idle2.wem"
        },
        "76116bf97888c069": {
            "hash": "76116bf97888c069",
            "directory": "External14",
            "voiceContent": "Ayo and I came up with the name together! I had already decided on the first part, turbo, and then I chose twirly because I noticed it looked a lot like Ayo in action. I often race against Ayo on it, and I've even won",
            "sourceName": "vo_kachina_dialog_idle.wem"
        },
        "78b457255c0968fe": {
            "hash": "78b457255c0968fe",
            "directory": "External15",
            "voiceContent": "After I received my Ancient Name, Uncle Pacal took me to see her and asked her to make Turbo Twirly for me. Her craftsmanship really is out of this world!Later, we discussed our experiences collecting and storing gems, and even admired each other's collections. Everything in her collection is in top condition, so she must take great care of them. She seems to take a more... casual approach to her own life, though... Once, I went looking for her, and couldn't find her for ages! I eventually found her basking in the sunshine in a big tree, sound asleep..",
            "sourceName": "vo_kachina_teammate_xilonen_01.wem"
        },
        "791d999edfb56ccf": {
            "hash": "791d999edfb56ccf",
            "directory": "External15",
            "voiceContent": "SFX",
            "sourceName": "vo_kachina_explore_climb_breath_02.wem"
        },
        "7e3ea73caf34aaf7": {
            "hash": "7e3ea73caf34aaf7",
            "directory": "External15",
            "voiceContent": "Are my ears... trembling? No, I'm not nervous... I'm just really happy. Sorry, but I can't really control them, they're way too excited right now. Here, I'll... let me just cover them up",
            "sourceName": "vo_kachina_starUp_01.wem"
        },
        "7f7bee547067469a": {
            "hash": "7f7bee547067469a",
            "directory": "External15",
            "voiceContent": "If you're bored, why don't we take a look at my collection together? If something catches your eye, feel free to take it",
            "sourceName": "vo_kachina_character_idle_03.wem"
        },
        "7fc31fea444b78e7": {
            "hash": "7fc31fea444b78e7",
            "directory": "External15",
            "voiceContent": "Before, when I wanted to become stronger, I asked Iansan to train me. She had me do all sorts of high-intensity workouts, and I often only managed to get through them by pushing myself to the limit. Luckily, she always knew just the right amount of training for me, so I still had just enough energy to make my way home after each session... I'm really grateful to her",
            "sourceName": "vo_kachina_teammate_iansan_01.wem"
        },
        "810121c74b8cbc99": {
            "hash": "810121c74b8cbc99",
            "directory": "External16",
            "voiceContent": "Let 'er rip",
            "sourceName": "vo_kachina_battle_skill1_01.wem"
        },
        "85f39d25ddf468f2": {
            "hash": "85f39d25ddf468f2",
            "directory": "External16",
            "voiceContent": "Don't forget about me",
            "sourceName": "vo_kachina_life_less30_teammate_01.wem"
        },
        "8ac9db7598896685": {
            "hash": "8ac9db7598896685",
            "directory": "External17",
            "voiceContent": "SFX",
            "sourceName": "vo_kachina_battle_hit_h_03.wem"
        },
        "8bbcaf8742dbf9ff": {
            "hash": "8bbcaf8742dbf9ff",
            "directory": "External17",
            "voiceContent": "SFX",
            "sourceName": "vo_kachina_battle_hit_h_05.wem"
        },
        "8cf4a0337c3302db": {
            "hash": "8cf4a0337c3302db",
            "directory": "External17",
            "voiceContent": "Clear the area",
            "sourceName": "vo_kachina_battle_skill3_01.wem"
        },
        "8fb24ee199653abb": {
            "hash": "8fb24ee199653abb",
            "directory": "External17",
            "voiceContent": "When I saw this shiny Vision for the first time, I really thought my eyes were playing a trick on me... It's more shiny than any ore I've ever seen. Even though I'm nowhere near as strong as a legendary hero right now, if one day, my story could inspire someone else, I'd be the happiest person in the world. Really, just one person would be enough..",
            "sourceName": "vo_kachina_dialog_pendant_01.wem"
        },
        "8fdaa38c07ae64e0": {
            "hash": "8fdaa38c07ae64e0",
            "directory": "External17",
            "voiceContent": "I'm not sleepy, so if you want to take a nap, I'll keep watch. There are a lot of things that I'm not that good at, but my ears are still plenty sharp! I can hear trouble coming from a mile away",
            "sourceName": "vo_kachina_dialog_greetingNoon.wem"
        },
        "91838c45299676f5": {
            "hash": "91838c45299676f5",
            "directory": "External18",
            "voiceContent": "Get back",
            "sourceName": "vo_kachina_battle_skill3_03.wem"
        },
        "9289dcea1179c59d": {
            "hash": "9289dcea1179c59d",
            "directory": "External18",
            "voiceContent": "SFX",
            "sourceName": "vo_kachina_explore_sprint_start_03.wem"
        },
        "934e1f729d32bd13": {
            "hash": "934e1f729d32bd13",
            "directory": "External18",
            "voiceContent": "Mualani gave me a huge hat once. It was super cool, and was perfect for blocking the sun, so I really loved it. Over time, though, it kind of turned into a felt hat... In the end, I had to get this hat instead, just because Saurian fur won't get stuck to it",
            "sourceName": "vo_kachina_dialog_annoyed_01.wem"
        },
        "967d3ee94ed23f87": {
            "hash": "967d3ee94ed23f87",
            "directory": "External18",
            "voiceContent": "I never could have dreamed that the Pyro Archon herself would one day call me a hero of Natlan... She's the idol of every warrior in our land, so being recognized by her is like... *sniffle* I just get overwhelmed every time I think about it, sorry... *sniffle* Sorry, sorry! I shouldn't have started crying..",
            "sourceName": "vo_kachina_teammate_mavuika_01.wem"
        },
        "9af284fa63804f36": {
            "hash": "9af284fa63804f36",
            "directory": "External19",
            "voiceContent": "Please pick one you like! Just think of it as a symbol of our friendship. I've brought all of my best and shiniest ores, so come on, take one! I'll be really happy if you do",
            "sourceName": "vo_kachina_dialog_close1.wem"
        },
        "9b4399a206db9fe2": {
            "hash": "9b4399a206db9fe2",
            "directory": "External19",
            "voiceContent": "SFX",
            "sourceName": "vo_kachina_explore_fly_start_03.wem"
        },
        "9c6d7db3b15d8fb4": {
            "hash": "9c6d7db3b15d8fb4",
            "directory": "External19",
            "voiceContent": "SFX",
            "sourceName": "vo_kachina_explore_fly_start_01.wem"
        },
        "9d9314f9b23eca59": {
            "hash": "9d9314f9b23eca59",
            "directory": "External19",
            "voiceContent": "Do you also like collecting shiny rocks? I mean, who wouldn't want to? They're so pretty",
            "sourceName": "vo_kachina_chest_open_02.wem"
        },
        "9e9088a739e64954": {
            "hash": "9e9088a739e64954",
            "directory": "External19",
            "voiceContent": "C'mon... Pull yourself together, Kachina",
            "sourceName": "vo_kachina_life_less30_02.wem"
        },
        "a08bc401c0e2d682": {
            "hash": "a08bc401c0e2d682",
            "directory": "External20",
            "voiceContent": "Uncle Pacal is really nice to me! Whenever other people in the tribe talk bad about me, he always defends me. Still... I feel bad whenever he has to do that. After all, I need to win everyone's respect with my own hands..",
            "sourceName": "vo_kachina_friendship_03.wem"
        },
        "a0b8c88a52e44248": {
            "hash": "a0b8c88a52e44248",
            "directory": "External20",
            "voiceContent": "This is the first gem I found. It's such a pretty shade of green, don't you think? It was originally one half of a pair, but I gave the other one to Mualani. Look, the pattern on it looks just like flowing water! Oh, and this one, too — it might look black at first glance, but put it under the sun, and you'll see all kinds of a rainbow of color! Hehe, I built this collection, one stone at a time",
            "sourceName": "vo_kachina_pref_hobby.wem"
        },
        "a313626a7e6600a1": {
            "hash": "a313626a7e6600a1",
            "directory": "External20",
            "voiceContent": "Let's go roll around in the snow together! Hehe, don't worry, I won't hide in the snow before suddenly jumping out at you like Ayo does",
            "sourceName": "vo_kachina_weather_snowy_01.wem"
        },
        "a3b90d3340a30bae": {
            "hash": "a3b90d3340a30bae",
            "directory": "External20",
            "voiceContent": "SFX",
            "sourceName": "vo_kachina_battle_attacklight_06.wem"
        },
        "a614e2574d8c274c": {
            "hash": "a614e2574d8c274c",
            "directory": "External20",
            "voiceContent": "Whoa, is this for me? It's super delicious! I'm going to eat slowly, so I can savor every bite..",
            "sourceName": "vo_kachina_spice_pref_01.wem"
        },
        "a7dc2839d035d034": {
            "hash": "a7dc2839d035d034",
            "directory": "External20",
            "voiceContent": "Did you know? Spinel fruit are shaped just like gems! Now, if only they had the same shelf-life as actual gems..",
            "sourceName": "vo_kachina_pref_gift_01.wem"
        },
        "a8ecb95429158210": {
            "hash": "a8ecb95429158210",
            "directory": "External21",
            "voiceContent": "You really care a lot about me... *sniffle* Ugh, I didn't mean to cry, but I'm just... so touched by your kindness",
            "sourceName": "vo_kachina_starUp_02.wem"
        },
        "aa6c204070b51670": {
            "hash": "aa6c204070b51670",
            "directory": "External21",
            "voiceContent": "Come look at this gem! When you hold it up under the sun, it almost looks like it's got a whole rainbow hiding inside",
            "sourceName": "vo_kachina_weather_sunny_01.wem"
        },
        "af24eef6b0b5719b": {
            "hash": "af24eef6b0b5719b",
            "directory": "External21",
            "voiceContent": "Whoa! I can... join the team",
            "sourceName": "vo_kachina_teamJoin_01.wem"
        },
        "afd8e37e8b05fa8f": {
            "hash": "afd8e37e8b05fa8f",
            "directory": "External21",
            "voiceContent": "It was Mualani who introduced me to him! To be honest, I was a little scared of him at first, because his eyes... well, he's got a scary look. It was only later that I found out that he secretly taught my bullies a lesson. But when I tried to give him a gift to thank him, he refused to take it. He said something along the lines of having already received enough compensation..",
            "sourceName": "vo_kachina_teammate_kinich_01.wem"
        },
        "b04edb085b376fb5": {
            "hash": "b04edb085b376fb5",
            "directory": "External22",
            "voiceContent": "Another chance to learn from you",
            "sourceName": "vo_kachina_teamJoin_03.wem"
        },
        "b2ec0050f406bf97": {
            "hash": "b2ec0050f406bf97",
            "directory": "External22",
            "voiceContent": "SFX",
            "sourceName": "vo_kachina_explore_climb_01.wem"
        },
        "b4091d108676475a": {
            "hash": "b4091d108676475a",
            "directory": "External22",
            "voiceContent": "SFX",
            "sourceName": "vo_kachina_battle_attacklight_02.wem"
        },
        "b5a17de6e3637ab2": {
            "hash": "b5a17de6e3637ab2",
            "directory": "External22",
            "voiceContent": "SFX",
            "sourceName": "vo_kachina_battle_hit_l_04.wem"
        },
        "b77bec62a16be6b1": {
            "hash": "b77bec62a16be6b1",
            "directory": "External22",
            "voiceContent": "SFX",
            "sourceName": "vo_kachina_explore_climb_03.wem"
        },
        "b7b97b2cd4280fd5": {
            "hash": "b7b97b2cd4280fd5",
            "directory": "External22",
            "voiceContent": "I'm here! Just leave it to me",
            "sourceName": "vo_kachina_life_less30_teammate_02.wem"
        },
        "b8c8dcda308eb8bd": {
            "hash": "b8c8dcda308eb8bd",
            "directory": "External23",
            "voiceContent": "SFX",
            "sourceName": "vo_kachina_battle_attackheavy_02.wem"
        },
        "b9d4cbb6f74f5088": {
            "hash": "b9d4cbb6f74f5088",
            "directory": "External23",
            "voiceContent": "SFX",
            "sourceName": "vo_kachina_explore_climb_breath_01.wem"
        },
        "ba3281a5ca1adfa5": {
            "hash": "ba3281a5ca1adfa5",
            "directory": "External23",
            "voiceContent": "Shockwave",
            "sourceName": "vo_kachina_battle_skill1_05.wem"
        },
        "bb3e1cb0dd5e89ef": {
            "hash": "bb3e1cb0dd5e89ef",
            "directory": "External23",
            "voiceContent": "Happy birthday! This is for you. It's a pika carved from Iridescent Opal. Iridescent Opal's quite warm to the touch, but it doesn't really stand out, so it's easy to miss it underground. The more you carry it with you, though, the shinier it gets! It's one of my favorite gems, so I hope you'll like it too",
            "sourceName": "vo_kachina_pref_birthday_01.wem"
        },
        "bb4096c5460c7b9e": {
            "hash": "bb4096c5460c7b9e",
            "directory": "External23",
            "voiceContent": "SFX",
            "sourceName": "vo_kachina_explore_idle_01.wem"
        },
        "bc69cad6f08d4140": {
            "hash": "bc69cad6f08d4140",
            "directory": "External23",
            "voiceContent": "SFX",
            "sourceName": "vo_kachina_explore_idle_03.wem"
        },
        "bca15950c432ef1e": {
            "hash": "bca15950c432ef1e",
            "directory": "External23",
            "voiceContent": "Rain makes the soil all muddy and soft, so you've got to be even more careful than usual when you're mining",
            "sourceName": "vo_kachina_weather_heavyRain_01.wem"
        },
        "bcca2041a8ffc8c2": {
            "hash": "bcca2041a8ffc8c2",
            "directory": "External23",
            "voiceContent": "Thank you for taking the time to make something for me! I—I promise that I'll finish this. Just... give me a few more minutes",
            "sourceName": "vo_kachina_spice_dislike_01.wem"
        },
        "c1cb822b71159799": {
            "hash": "c1cb822b71159799",
            "directory": "External24",
            "voiceContent": "I've always known that crying won't solve anything, and I've never heard a legend talk about the hero crying in front of their friends, either. I really want to hold back my tears, but I just can't... Huh? It's okay? Tears are a good way to let out your emotions? Do... Do you really think so? *sniffle* Thank you, thank you... Oh no, why am I crying again",
            "sourceName": "vo_kachina_friendship_04.wem"
        },
        "cc74219f5a764af8": {
            "hash": "cc74219f5a764af8",
            "directory": "External25",
            "voiceContent": "SFX",
            "sourceName": "vo_kachina_battle_hit_h_06.wem"
        },
        "d1e2db3a33c5df51": {
            "hash": "d1e2db3a33c5df51",
            "directory": "External26",
            "voiceContent": "SFX",
            "sourceName": "vo_kachina_battle_attacklight_05.wem"
        },
        "d6e13c1093963b89": {
            "hash": "d6e13c1093963b89",
            "directory": "External26",
            "voiceContent": "SFX",
            "sourceName": "vo_kachina_battle_hit_l_03.wem"
        },
        "daf72f665f2328ab": {
            "hash": "daf72f665f2328ab",
            "directory": "External27",
            "voiceContent": "SFX",
            "sourceName": "vo_kachina_battle_hit_h_01.wem"
        },
        "dded4d8e4aca2216": {
            "hash": "dded4d8e4aca2216",
            "directory": "External27",
            "voiceContent": "SFX",
            "sourceName": "vo_kachina_battle_hit_h_04.wem"
        },
        "e2b770dad813f4e3": {
            "hash": "e2b770dad813f4e3",
            "directory": "External28",
            "voiceContent": "SFX",
            "sourceName": "vo_kachina_explore_sprint_start_01.wem"
        },
        "e4a7dab059df48b7": {
            "hash": "e4a7dab059df48b7",
            "directory": "External28",
            "voiceContent": "There are a lot of legends about heroes in Natlan, and my favorite is the one about Lord Traore! How incredibly cool is it to be able to seal the Abyss beneath the ground as an ordinary mortal? Oh, that reminds me... you've been to a bunch of countries in Teyvat, so you must know a lot of legends, right? I'm super curious... Could you tell me some of them when you can find the time",
            "sourceName": "vo_kachina_dialog_close.wem"
        },
        "e85a6fff83ea210f": {
            "hash": "e85a6fff83ea210f",
            "directory": "External29",
            "voiceContent": "SFX",
            "sourceName": "vo_kachina_battle_hit_l_01.wem"
        },
        "e939e123768ebcb8": {
            "hash": "e939e123768ebcb8",
            "directory": "External29",
            "voiceContent": "SFX",
            "sourceName": "vo_kachina_explore_jump_05.wem"
        },
        "f1c4bf64e68ecfa8": {
            "hash": "f1c4bf64e68ecfa8",
            "directory": "External30",
            "voiceContent": "SFX",
            "sourceName": "vo_kachina_battle_attackmid_02.wem"
        },
        "f44ac87c58bdb396": {
            "hash": "f44ac87c58bdb396",
            "directory": "External30",
            "voiceContent": "*sniffle* I don't know how I managed to screw things up again today... Nooo, I don't wanna cry, but I just can't seem to help myself... *sniffle*... Ahh! D—Didn't we both already say good night to each other? Th—Thank you for staying up and comforting me though, it means a lot..",
            "sourceName": "vo_kachina_dialog_greetingNight2.wem"
        },
        "f76037a7231541e6": {
            "hash": "f76037a7231541e6",
            "directory": "External30",
            "voiceContent": "SFX",
            "sourceName": "vo_kachina_explore_climb_breath_03.wem"
        },
        "f9d3b5f84523034b": {
            "hash": "f9d3b5f84523034b",
            "directory": "External31",
            "voiceContent": "My family, huh... I'm the middle child of my family. My Dad's placed most of his hopes on my older sister, and my Mom has to spend a lot of time taking care of my younger sister. Our life isn't exactly easy, so I've got to be a good girl, and grow up quickly... Or at the very least, make sure they won't have to constantly worry about me",
            "sourceName": "vo_kachina_friendship_02.wem"
        },
        "fb22eeea7e1ec46b": {
            "hash": "fb22eeea7e1ec46b",
            "directory": "External31",
            "voiceContent": "SFX",
            "sourceName": "vo_kachina_explore_jump_02.wem"
        },
        "fd2e9bf764016cce": {
            "hash": "fd2e9bf764016cce",
            "directory": "External31",
            "voiceContent": "Mualani's my first good friend! Before I met her, I never even knew that people as sweet as her existed, or how many fun things there are in the world! Look, this is a photo of us! She said we should jump right when they took the photo... I look a bit stiff? Hehe, you caught me! A lot of people were staring at us when we took this photo, so I was really nervous..",
            "sourceName": "vo_kachina_teammate_mualani_01.wem"
        }
    }
}